aie_ipyleaflet-0.15.1.data/data/etc/jupyter/nbconfig/notebook.d/jupyter-leaflet.json
aie_ipyleaflet-0.15.1.data/data/share/jupyter/labextensions/jupyter-leaflet/package.json
aie_ipyleaflet-0.15.1.data/data/share/jupyter/labextensions/jupyter-leaflet/static/056dcd0b0dea7c78019243311551d64b.png
aie_ipyleaflet-0.15.1.data/data/share/jupyter/labextensions/jupyter-leaflet/static/07f16cd155661436fe27959eab15c820.png
aie_ipyleaflet-0.15.1.data/data/share/jupyter/labextensions/jupyter-leaflet/static/0b50583aa1b8ff230b57b92263e47a3e.png
aie_ipyleaflet-0.15.1.data/data/share/jupyter/labextensions/jupyter-leaflet/static/0f2c10250081cf1bd9a4d2250b80dba6.png
aie_ipyleaflet-0.15.1.data/data/share/jupyter/labextensions/jupyter-leaflet/static/138.df2290bc7a0cbf18c473.js
aie_ipyleaflet-0.15.1.data/data/share/jupyter/labextensions/jupyter-leaflet/static/2273e3d8ad9264b7daa5bdbf8e6b47f8.png
aie_ipyleaflet-0.15.1.data/data/share/jupyter/labextensions/jupyter-leaflet/static/243.d9d134ad2ffdfb9205b3.js
aie_ipyleaflet-0.15.1.data/data/share/jupyter/labextensions/jupyter-leaflet/static/243.d9d134ad2ffdfb9205b3.js.LICENSE.txt
aie_ipyleaflet-0.15.1.data/data/share/jupyter/labextensions/jupyter-leaflet/static/280.5de51328720a28cc66e7.js
aie_ipyleaflet-0.15.1.data/data/share/jupyter/labextensions/jupyter-leaflet/static/292.abb15e393ff2062a9743.js
aie_ipyleaflet-0.15.1.data/data/share/jupyter/labextensions/jupyter-leaflet/static/340.06cd3bdbc92899d7cb95.js
aie_ipyleaflet-0.15.1.data/data/share/jupyter/labextensions/jupyter-leaflet/static/35.75d7ebb67cdd9a91223a.js
aie_ipyleaflet-0.15.1.data/data/share/jupyter/labextensions/jupyter-leaflet/static/35ae4b5f1bf198c6d955618b85710d05.png
aie_ipyleaflet-0.15.1.data/data/share/jupyter/labextensions/jupyter-leaflet/static/366.548c239572b0d4db46f3.js
aie_ipyleaflet-0.15.1.data/data/share/jupyter/labextensions/jupyter-leaflet/static/401d815dc206b8dc1b17cd0e37695975.png
aie_ipyleaflet-0.15.1.dist-info/LICENSE
aie_ipyleaflet-0.15.1.dist-info/METADATA
aie_ipyleaflet-0.15.1.dist-info/WHEEL
aie_ipyleaflet-0.15.1.dist-info/top_level.txt
aie_ipyleaflet-0.15.1.dist-info/RECORD
